resolvedcap/__init__.py
resolvedcap/resolved.py
resolvedcap-0.1.dist-info/LICENSE
resolvedcap-0.1.dist-info/METADATA
resolvedcap-0.1.dist-info/WHEEL
resolvedcap-0.1.dist-info/top_level.txt
resolvedcap-0.1.dist-info/RECORD
